traceroute/__init__.py
traceroute/__main__.py
traceroute/lorem.py
traceroute/traceroute.py
wintraceroute-1.3.20.dist-info/licenses/LICENSE
wintraceroute-1.3.20.dist-info/METADATA
wintraceroute-1.3.20.dist-info/WHEEL
wintraceroute-1.3.20.dist-info/entry_points.txt
wintraceroute-1.3.20.dist-info/top_level.txt
wintraceroute-1.3.20.dist-info/RECORD
