Metadata-Version: 2.4
Name: WinTraceroute
Version: 1.3.20
Summary: A mostly *NIX-traceroute-like -- but very basic -- tracert/traceroute IPv4 alternative built on scapy.
Author-email: Nico Rittinghaus <nico@ritti.ng>
License:                     GNU GENERAL PUBLIC LICENSE
Project-URL: Homepage, https://github.com/NiRit100/WinTraceroute
Keywords: traceroute,tracert,network,routing,scapy
Classifier: Programming Language :: Python
Classifier: Programming Language :: Python :: 3
Classifier: Development Status :: 4 - Beta
Requires-Python: >=3.8
License-File: LICENSE
Requires-Dist: scapy==2.5.0
Provides-Extra: dev
Requires-Dist: pip-tools; extra == "dev"
Requires-Dist: pytest; extra == "dev"
Requires-Dist: pyinstaller==6.16.0; extra == "dev"
Dynamic: license-file
